sea_cli/__init__.py
sea_cli/cli.py
sea_cli/entropy.py
sea_cli/export.py
sea_cli/features.py
sea_cli/io.py
sea_cli/pipeline.py
sea_cli/plotting.py
sea_cli-0.1.6.dist-info/licenses/LICENSE
sea_cli-0.1.6.dist-info/METADATA
sea_cli-0.1.6.dist-info/WHEEL
sea_cli-0.1.6.dist-info/entry_points.txt
sea_cli-0.1.6.dist-info/top_level.txt
sea_cli-0.1.6.dist-info/RECORD
