Metadata-Version: 2.4
Name: sea-cli
Version: 0.1.6
Summary: A command-line utility for Structured Entropy Analysis (SEA)
Home-page: https://github.com/cyril-pierro/sea-cli
Author: Ezekiel Edward Netty-Oppong & Per Badasu & Emmanuel Essel Mensah
Author-email: misterezekieledward@gmail.com
Classifier: Programming Language :: Python :: 3
Classifier: License :: OSI Approved :: MIT License
Classifier: Operating System :: OS Independent
Classifier: Development Status :: 4 - Beta
Classifier: Topic :: Scientific/Engineering
Requires-Python: >=3.6
License-File: LICENSE
Requires-Dist: numpy
Requires-Dist: scipy
Requires-Dist: scikit-learn
Requires-Dist: matplotlib
Requires-Dist: click
Requires-Dist: pyyaml
Dynamic: author
Dynamic: author-email
Dynamic: classifier
Dynamic: description
Dynamic: description-content-type
Dynamic: home-page
Dynamic: license-file
Dynamic: requires-dist
Dynamic: requires-python
Dynamic: summary
